check_po/__init__.py
check_po/_compat.py
check_po/check_urls.py
check_po/pochecker.py
check_po/podiff.py
check_po/tests/__init__.py
check_po/tests/check_po.py
check_po/tests/check_urls.py
check_po/tests/podiff.py
check_po-1.0.0.dist-info/DESCRIPTION.rst
check_po-1.0.0.dist-info/METADATA
check_po-1.0.0.dist-info/RECORD
check_po-1.0.0.dist-info/WHEEL
check_po-1.0.0.dist-info/entry_points.txt
check_po-1.0.0.dist-info/metadata.json
check_po-1.0.0.dist-info/pbr.json
check_po-1.0.0.dist-info/top_level.txt
