Metadata-Version: 2.0
Name: check-po
Version: 1.0.0
Summary: Check_po to verify if everything is translated and that no fuzzy are still here.
Home-page: https://github.com/peopledoc/check_po
Author: Rémy Hubscher
Author-email: hubscher.remy@gmail.com
License: GPLv3+
Keywords: translation
Requires-Dist: polib
